pctx_sandbox/__init__.py
pctx_sandbox/client.py
pctx_sandbox/decorator.py
pctx_sandbox/exceptions.py
pctx_sandbox/agent/__init__.py
pctx_sandbox/agent/pool.py
pctx_sandbox/agent/simple_agent.py
pctx_sandbox/agent/worker.py
pctx_sandbox/platform/__init__.py
pctx_sandbox/platform/base.py
pctx_sandbox/platform/podman.py
pctx_sandbox-0.1.0.dist-info/licenses/LICENSE
pctx_sandbox-0.1.0.dist-info/METADATA
pctx_sandbox-0.1.0.dist-info/WHEEL
pctx_sandbox-0.1.0.dist-info/top_level.txt
pctx_sandbox-0.1.0.dist-info/RECORD
