Metadata-Version: 2.4
Name: pctx-sandbox
Version: 0.1.0
Summary: A Python decorator that transparently executes functions in isolated microVMs
Author-email: Port of Context <hello@portofcontext.com>
License: MIT
Project-URL: Homepage, https://github.com/portofcontext/pctx-sandbox
Project-URL: Documentation, https://github.com/portofcontext/pctx-sandbox#readme
Project-URL: Repository, https://github.com/portofcontext/pctx-sandbox
Project-URL: Issues, https://github.com/portofcontext/pctx-sandbox/issues
Keywords: sandbox,ai-agent,microvm,isolation,security
Classifier: Development Status :: 3 - Alpha
Classifier: Intended Audience :: Developers
Classifier: License :: OSI Approved :: MIT License
Classifier: Programming Language :: Python :: 3
Classifier: Programming Language :: Python :: 3.10
Classifier: Programming Language :: Python :: 3.11
Classifier: Programming Language :: Python :: 3.12
Requires-Python: >=3.10
License-File: LICENSE
Requires-Dist: cloudpickle>=3.0.0
Requires-Dist: httpx>=0.25.0
Requires-Dist: msgpack>=1.0.0
Requires-Dist: fastapi>=0.100.0
Requires-Dist: uvicorn[standard]>=0.20.0
Requires-Dist: pydantic>=2.0.0
Provides-Extra: dev
Requires-Dist: pytest>=9.0.2; extra == "dev"
Requires-Dist: pytest-cov>=7.0.0; extra == "dev"
Requires-Dist: pytest-asyncio>=1.3.0; extra == "dev"
Requires-Dist: pytest-mock>=3.15.1; extra == "dev"
Requires-Dist: ruff>=0.14.10; extra == "dev"
Dynamic: license-file
